ram/ram.v
module ram(
  input debug,
  input prg_mode,
  input [7:0] prg_data,
  input [3:0] address,
  input wr_en,
  input re_en,
  inout [7:0] bus
  );

  reg [7:0] ram [0:15];
  assign bus = re_en ? ram[address] : 8'bzzzzzzzz;

  initial begin
    for(integer i = 0; i < 16; i++) begin
      // ram[i] = 8'b00000000;
      $readmemb("ram/ram.txt", ram);
    end
  end

  always @(posedge wr_en) begin
    if(prg_mode) begin
      if(debug) $display("Program RAM address: %b prg_data: %b", address, prg_data);
      ram[address] <= prg_data;
    end
    else begin
      if(debug) $display("RAM write address: %b bus: %b", address, bus);
      ram[address] <= bus;
    end
  end

  always @(posedge re_en) begin
    if(debug) $display("Read\tRAM address: %b  ram[address]: %b", address, ram[address]);
  end

endmodule

ram/ram_tb.v
`timescale 1 ns/10 ps  // time-unit = 1 ns, precision = 10 ps
`include "ram.v"
module ram_tb();
  reg clk = 0;
  reg debug = 1;
  reg prg_mode = 0;
  reg [7:0] prg_data;
  reg [3:0] address;
  reg wr_en= 1;
  reg re_en;
  wire [7:0] bus;

  reg [7:0] bus_strap;

  assign bus = bus_strap;
  ram r(
    .debug(debug),
    .prg_mode(prg_mode),
    .prg_data(prg_data),
    .address(address),
    .wr_en(wr_en),
    .re_en(re_en),
    .bus(bus)
    );

  initial begin
    clk = 1'b0;
    forever #2 clk = ~clk;
  end

  initial begin
    $dumpfile("ram_tb.vcd");
    $dumpvars(0, ram_tb);

    for(integer j = 0; j < 2; j++) begin
      prg_mode = !j;
      $display("\nprg_mode: %b", prg_mode);

      for(integer i = 0; i < 12; i = i + 1) begin
        wr_en = i % 2 == 0;
        prg_data = i * 12;
        bus_strap = i * 3;
        address = i; #20;
      end
      $display("\nprg_mode: %b", prg_mode);

      for(integer i = 0; i < 12; i = i + 1) begin
        re_en = i % 2 == 0;
        prg_data = i * 12;
        address = i; #20;
      end
    end

    $display("Howdy");
    $finish;
  end
endmodule

ram/ram_tb.vcd
$date
	Mon Mar 14 21:53:52 2022
$end
$version
	Icarus Verilog
$end
$timescale
	10ps
$end
$scope module ram_tb $end
$var wire 8 ! bus [7:0] $end
$var reg 4 " address [3:0] $end
$var reg 8 # bus_strap [7:0] $end
$var reg 1 $ clk $end
$var reg 1 % debug $end
$var reg 8 & prg_data [7:0] $end
$var reg 1 ' prg_mode $end
$var reg 1 ( re_en $end
$var reg 1 ) wr_en $end
$scope module r $end
$var wire 4 * address [3:0] $end
$var wire 8 + bus [7:0] $end
$var wire 1 % debug $end
$var wire 8 , prg_data [7:0] $end
$var wire 1 ' prg_mode $end
$var wire 1 ( re_en $end
$var wire 1 ) wr_en $end
$scope begin $ivl_for_loop0 $end
$var integer 32 - i [31:0] $end
$upscope $end
$upscope $end
$scope begin $ivl_for_loop1 $end
$var integer 32 . i [31:0] $end
$upscope $end
$scope begin $ivl_for_loop2 $end
$var integer 32 / j [31:0] $end
$scope begin $ivl_for_loop3 $end
$var integer 32 0 i [31:0] $end
$upscope $end
$scope begin $ivl_for_loop4 $end
$var integer 32 1 i [31:0] $end
$upscope $end
$upscope $end
$upscope $end
$enddefinitions $end
#0
$dumpvars
bx 1
bx 0
bx /
b0 .
b10000 -
bx ,
bx +
b0 *
1)
1(
0'
bx &
0%
0$
bx #
b0 "
bx !
$end
#200
1$
#400
0$
#600
1$
#800
0$
#1000
1$
#1200
0$
#1400
1$
#1600
0$
#1800
1$
#2000
b100 !
b100 +
0$
b1 "
b1 *
b1 .
#2200
1$
#2400
0$
#2600
1$
#2800
0$
#3000
1$
#3200
0$
#3400
1$
#3600
0$
#3800
1$
#4000
b1000 !
b1000 +
0$
b10 "
b10 *
b10 .
#4200
1$
#4400
0$
#4600
1$
#4800
0$
#5000
1$
#5200
0$
#5400
1$
#5600
0$
#5800
1$
#6000
b1100 !
b1100 +
0$
b11 "
b11 *
b11 .
#6200
1$
#6400
0$
#6600
1$
#6800
0$
#7000
1$
#7200
0$
#7400
1$
#7600
0$
#7800
1$
#8000
b10000 !
b10000 +
0$
b100 "
b100 *
b100 .
#8200
1$
#8400
0$
#8600
1$
#8800
0$
#9000
1$
#9200
0$
#9400
1$
#9600
0$
#9800
1$
#10000
b10100 !
b10100 +
0$
b101 "
b101 *
b101 .
#10200
1$
#10400
0$
#10600
1$
#10800
0$
#11000
1$
#11200
0$
#11400
1$
#11600
0$
#11800
1$
#12000
b11000 !
b11000 +
0$
b110 "
b110 *
b110 .
#12200
1$
#12400
0$
#12600
1$
#12800
0$
#13000
1$
#13200
0$
#13400
1$
#13600
0$
#13800
1$
#14000
b11100 !
b11100 +
0$
b111 "
b111 *
b111 .
#14200
1$
#14400
0$
#14600
1$
#14800
0$
#15000
1$
#15200
0$
#15400
1$
#15600
0$
#15800
1$
#16000
b100000 !
b100000 +
0$
b1000 "
b1000 *
b1000 .
#16200
1$
#16400
0$
#16600
1$
#16800
0$
#17000
1$
#17200
0$
#17400
1$
#17600
0$
#17800
1$
#18000
b100100 !
b100100 +
0$
b1001 "
b1001 *
b1001 .
#18200
1$
#18400
0$
#18600
1$
#18800
0$
#19000
1$
#19200
0$
#19400
1$
#19600
0$
#19800
1$
#20000
b10100 !
b10100 +
0$
b1010 "
b1010 *
b1010 .
#20200
1$
#20400
0$
#20600
1$
#20800
0$
#21000
1$
#21200
0$
#21400
1$
#21600
0$
#21800
1$
#22000
b101100 !
b101100 +
0$
b1011 "
b1011 *
b1011 .
#22200
1$
#22400
0$
#22600
1$
#22800
0$
#23000
1$
#23200
0$
#23400
1$
#23600
0$
#23800
1$
#24000
b110000 !
b110000 +
0$
b1100 "
b1100 *
b1100 .
#24200
1$
#24400
0$
#24600
1$
#24800
0$
#25000
1$
#25200
0$
#25400
1$
#25600
0$
#25800
1$
#26000
b110100 !
b110100 +
0$
b1101 "
b1101 *
b1101 .
#26200
1$
#26400
0$
#26600
1$
#26800
0$
#27000
1$
#27200
0$
#27400
1$
#27600
0$
#27800
1$
#28000
b111000 !
b111000 +
0$
b1110 "
b1110 *
b1110 .
#28200
1$
#28400
0$
#28600
1$
#28800
0$
#29000
1$
#29200
0$
#29400
1$
#29600
0$
#29800
1$
#30000
b111100 !
b111100 +
0$
b1111 "
b1111 *
b1111 .
#30200
1$
#30400
0$
#30600
1$
#30800
0$
#31000
1$
#31200
0$
#31400
1$
#31600
0$
#31800
1$
#32000
bx !
bx +
0$
b0 "
b0 *
b0 #
b0 &
b0 ,
b0 0
1'
b0 /
1%
b10000 .
#32200
1$
#32400
0$
#32600
1$
#32800
0$
#33000
1$
#33200
0$
#33400
1$
#33600
0$
#33800
1$
#34000
b100 !
b100 +
0$
b1 "
b1 *
b11 #
b1100 &
b1100 ,
0)
b1 0
#34200
1$
#34400
0$
#34600
1$
#34800
0$
#35000
1$
#35200
0$
#35400
1$
#35600
0$
#35800
1$
#36000
b11000 !
b11000 +
0$
b10 "
b10 *
b110 #
b11000 &
b11000 ,
1)
b10 0
#36200
1$
#36400
0$
#36600
1$
#36800
0$
#37000
1$
#37200
0$
#37400
1$
#37600
0$
#37800
1$
#38000
b1100 !
b1100 +
0$
b11 "
b11 *
b1001 #
b100100 &
b100100 ,
0)
b11 0
#38200
1$
#38400
0$
#38600
1$
#38800
0$
#39000
1$
#39200
0$
#39400
1$
#39600
0$
#39800
1$
#40000
b110000 !
b110000 +
0$
b100 "
b100 *
b1100 #
b110000 &
b110000 ,
1)
b100 0
#40200
1$
#40400
0$
#40600
1$
#40800
0$
#41000
1$
#41200
0$
#41400
1$
#41600
0$
#41800
1$
#42000
b10100 !
b10100 +
0$
b101 "
b101 *
b1111 #
b111100 &
b111100 ,
0)
b101 0
#42200
1$
#42400
0$
#42600
1$
#42800
0$
#43000
1$
#43200
0$
#43400
1$
#43600
0$
#43800
1$
#44000
b1001000 !
b1001000 +
0$
b110 "
b110 *
b10010 #
b1001000 &
b1001000 ,
1)
b110 0
#44200
1$
#44400
0$
#44600
1$
#44800
0$
#45000
1$
#45200
0$
#45400
1$
#45600
0$
#45800
1$
#46000
b11100 !
b11100 +
0$
b111 "
b111 *
b10101 #
b1010100 &
b1010100 ,
0)
b111 0
#46200
1$
#46400
0$
#46600
1$
#46800
0$
#47000
1$
#47200
0$
#47400
1$
#47600
0$
#47800
1$
#48000
b1100000 !
b1100000 +
0$
b1000 "
b1000 *
b11000 #
b1100000 &
b1100000 ,
1)
b1000 0
#48200
1$
#48400
0$
#48600
1$
#48800
0$
#49000
1$
#49200
0$
#49400
1$
#49600
0$
#49800
1$
#50000
b100100 !
b100100 +
0$
b1001 "
b1001 *
b11011 #
b1101100 &
b1101100 ,
0)
b1001 0
#50200
1$
#50400
0$
#50600
1$
#50800
0$
#51000
1$
#51200
0$
#51400
1$
#51600
0$
#51800
1$
#52000
b1111000 !
b1111000 +
0$
b1010 "
b1010 *
b11110 #
b1111000 &
b1111000 ,
1)
b1010 0
#52200
1$
#52400
0$
#52600
1$
#52800
0$
#53000
1$
#53200
0$
#53400
1$
#53600
0$
#53800
1$
#54000
b101100 !
b101100 +
0$
b1011 "
b1011 *
b100001 #
b10000100 &
b10000100 ,
0)
b1011 0
#54200
1$
#54400
0$
#54600
1$
#54800
0$
#55000
1$
#55200
0$
#55400
1$
#55600
0$
#55800
1$
#56000
bx !
bx +
0$
b0 "
b0 *
b0 &
b0 ,
b0 1
b1100 0
#56200
1$
#56400
0$
#56600
1$
#56800
0$
#57000
1$
#57200
0$
#57400
1$
#57600
0$
#57800
1$
#58000
b100001 !
b100001 +
0$
b1 "
b1 *
b1100 &
b1100 ,
0(
b1 1
#58200
1$
#58400
0$
#58600
1$
#58800
0$
#59000
1$
#59200
0$
#59400
1$
#59600
0$
#59800
1$
#60000
b11000 !
b11000 +
0$
b10 "
b10 *
b11000 &
b11000 ,
1(
b10 1
#60200
1$
#60400
0$
#60600
1$
#60800
0$
#61000
1$
#61200
0$
#61400
1$
#61600
0$
#61800
1$
#62000
b100001 !
b100001 +
0$
b11 "
b11 *
b100100 &
b100100 ,
0(
b11 1
#62200
1$
#62400
0$
#62600
1$
#62800
0$
#63000
1$
#63200
0$
#63400
1$
#63600
0$
#63800
1$
#64000
b110000 !
b110000 +
0$
b100 "
b100 *
b110000 &
b110000 ,
1(
b100 1
#64200
1$
#64400
0$
#64600
1$
#64800
0$
#65000
1$
#65200
0$
#65400
1$
#65600
0$
#65800
1$
#66000
b100001 !
b100001 +
0$
b101 "
b101 *
b111100 &
b111100 ,
0(
b101 1
#66200
1$
#66400
0$
#66600
1$
#66800
0$
#67000
1$
#67200
0$
#67400
1$
#67600
0$
#67800
1$
#68000
b1001000 !
b1001000 +
0$
b110 "
b110 *
b1001000 &
b1001000 ,
1(
b110 1
#68200
1$
#68400
0$
#68600
1$
#68800
0$
#69000
1$
#69200
0$
#69400
1$
#69600
0$
#69800
1$
#70000
b100001 !
b100001 +
0$
b111 "
b111 *
b1010100 &
b1010100 ,
0(
b111 1
#70200
1$
#70400
0$
#70600
1$
#70800
0$
#71000
1$
#71200
0$
#71400
1$
#71600
0$
#71800
1$
#72000
b1100000 !
b1100000 +
0$
b1000 "
b1000 *
b1100000 &
b1100000 ,
1(
b1000 1
#72200
1$
#72400
0$
#72600
1$
#72800
0$
#73000
1$
#73200
0$
#73400
1$
#73600
0$
#73800
1$
#74000
b100001 !
b100001 +
0$
b1001 "
b1001 *
b1101100 &
b1101100 ,
0(
b1001 1
#74200
1$
#74400
0$
#74600
1$
#74800
0$
#75000
1$
#75200
0$
#75400
1$
#75600
0$
#75800
1$
#76000
b1111000 !
b1111000 +
0$
b1010 "
b1010 *
b1111000 &
b1111000 ,
1(
b1010 1
#76200
1$
#76400
0$
#76600
1$
#76800
0$
#77000
1$
#77200
0$
#77400
1$
#77600
0$
#77800
1$
#78000
b100001 !
b100001 +
0$
b1011 "
b1011 *
b10000100 &
b10000100 ,
0(
b1011 1
#78200
1$
#78400
0$
#78600
1$
#78800
0$
#79000
1$
#79200
0$
#79400
1$
#79600
0$
#79800
1$
#80000
b0 !
b0 +
0$
b0 "
b0 *
b0 #
b0 &
b0 ,
1)
b0 0
0'
b1 /
b1100 1
#80200
1$
#80400
0$
#80600
1$
#80800
0$
#81000
1$
#81200
0$
#81400
1$
#81600
0$
#81800
1$
#82000
b11 !
b11 +
0$
b1 "
b1 *
b11 #
b1100 &
b1100 ,
0)
b1 0
#82200
1$
#82400
0$
#82600
1$
#82800
0$
#83000
1$
#83200
0$
#83400
1$
#83600
0$
#83800
1$
#84000
b110 !
b110 +
0$
b10 "
b10 *
b110 #
b11000 &
b11000 ,
1)
b10 0
#84200
1$
#84400
0$
#84600
1$
#84800
0$
#85000
1$
#85200
0$
#85400
1$
#85600
0$
#85800
1$
#86000
b1001 !
b1001 +
0$
b11 "
b11 *
b1001 #
b100100 &
b100100 ,
0)
b11 0
#86200
1$
#86400
0$
#86600
1$
#86800
0$
#87000
1$
#87200
0$
#87400
1$
#87600
0$
#87800
1$
#88000
b1100 !
b1100 +
0$
b100 "
b100 *
b1100 #
b110000 &
b110000 ,
1)
b100 0
#88200
1$
#88400
0$
#88600
1$
#88800
0$
#89000
1$
#89200
0$
#89400
1$
#89600
0$
#89800
1$
#90000
b1111 !
b1111 +
0$
b101 "
b101 *
b1111 #
b111100 &
b111100 ,
0)
b101 0
#90200
1$
#90400
0$
#90600
1$
#90800
0$
#91000
1$
#91200
0$
#91400
1$
#91600
0$
#91800
1$
#92000
b10010 !
b10010 +
0$
b110 "
b110 *
b10010 #
b1001000 &
b1001000 ,
1)
b110 0
#92200
1$
#92400
0$
#92600
1$
#92800
0$
#93000
1$
#93200
0$
#93400
1$
#93600
0$
#93800
1$
#94000
b10101 !
b10101 +
0$
b111 "
b111 *
b10101 #
b1010100 &
b1010100 ,
0)
b111 0
#94200
1$
#94400
0$
#94600
1$
#94800
0$
#95000
1$
#95200
0$
#95400
1$
#95600
0$
#95800
1$
#96000
b11000 !
b11000 +
0$
b1000 "
b1000 *
b11000 #
b1100000 &
b1100000 ,
1)
b1000 0
#96200
1$
#96400
0$
#96600
1$
#96800
0$
#97000
1$
#97200
0$
#97400
1$
#97600
0$
#97800
1$
#98000
b11011 !
b11011 +
0$
b1001 "
b1001 *
b11011 #
b1101100 &
b1101100 ,
0)
b1001 0
#98200
1$
#98400
0$
#98600
1$
#98800
0$
#99000
1$
#99200
0$
#99400
1$
#99600
0$
#99800
1$
#100000
b11110 !
b11110 +
0$
b1010 "
b1010 *
b11110 #
b1111000 &
b1111000 ,
1)
b1010 0
#100200
1$
#100400
0$
#100600
1$
#100800
0$
#101000
1$
#101200
0$
#101400
1$
#101600
0$
#101800
1$
#102000
b100001 !
b100001 +
0$
b1011 "
b1011 *
b100001 #
b10000100 &
b10000100 ,
0)
b1011 0
#102200
1$
#102400
0$
#102600
1$
#102800
0$
#103000
1$
#103200
0$
#103400
1$
#103600
0$
#103800
1$
#104000
0$
b0 "
b0 *
b0 &
b0 ,
1(
b0 1
b1100 0
#104200
1$
#104400
0$
#104600
1$
#104800
0$
#105000
1$
#105200
0$
#105400
1$
#105600
0$
#105800
1$
#106000
b100001 !
b100001 +
0$
b1 "
b1 *
b1100 &
b1100 ,
0(
b1 1
#106200
1$
#106400
0$
#106600
1$
#106800
0$
#107000
1$
#107200
0$
#107400
1$
#107600
0$
#107800
1$
#108000
b11 !
b11 +
0$
b10 "
b10 *
b11000 &
b11000 ,
1(
b10 1
#108200
1$
#108400
0$
#108600
1$
#108800
0$
#109000
1$
#109200
0$
#109400
1$
#109600
0$
#109800
1$
#110000
b100001 !
b100001 +
0$
b11 "
b11 *
b100100 &
b100100 ,
0(
b11 1
#110200
1$
#110400
0$
#110600
1$
#110800
0$
#111000
1$
#111200
0$
#111400
1$
#111600
0$
#111800
1$
#112000
b1001 !
b1001 +
0$
b100 "
b100 *
b110000 &
b110000 ,
1(
b100 1
#112200
1$
#112400
0$
#112600
1$
#112800
0$
#113000
1$
#113200
0$
#113400
1$
#113600
0$
#113800
1$
#114000
b100001 !
b100001 +
0$
b101 "
b101 *
b111100 &
b111100 ,
0(
b101 1
#114200
1$
#114400
0$
#114600
1$
#114800
0$
#115000
1$
#115200
0$
#115400
1$
#115600
0$
#115800
1$
#116000
b1111 !
b1111 +
0$
b110 "
b110 *
b1001000 &
b1001000 ,
1(
b110 1
#116200
1$
#116400
0$
#116600
1$
#116800
0$
#117000
1$
#117200
0$
#117400
1$
#117600
0$
#117800
1$
#118000
b100001 !
b100001 +
0$
b111 "
b111 *
b1010100 &
b1010100 ,
0(
b111 1
#118200
1$
#118400
0$
#118600
1$
#118800
0$
#119000
1$
#119200
0$
#119400
1$
#119600
0$
#119800
1$
#120000
b10101 !
b10101 +
0$
b1000 "
b1000 *
b1100000 &
b1100000 ,
1(
b1000 1
#120200
1$
#120400
0$
#120600
1$
#120800
0$
#121000
1$
#121200
0$
#121400
1$
#121600
0$
#121800
1$
#122000
b100001 !
b100001 +
0$
b1001 "
b1001 *
b1101100 &
b1101100 ,
0(
b1001 1
#122200
1$
#122400
0$
#122600
1$
#122800
0$
#123000
1$
#123200
0$
#123400
1$
#123600
0$
#123800
1$
#124000
b11011 !
b11011 +
0$
b1010 "
b1010 *
b1111000 &
b1111000 ,
1(
b1010 1
#124200
1$
#124400
0$
#124600
1$
#124800
0$
#125000
1$
#125200
0$
#125400
1$
#125600
0$
#125800
1$
#126000
b100001 !
b100001 +
0$
b1011 "
b1011 *
b10000100 &
b10000100 ,
0(
b1011 1
#126200
1$
#126400
0$
#126600
1$
#126800
0$
#127000
1$
#127200
0$
#127400
1$
#127600
0$
#127800
1$
#128000
0$
b10 /
b1100 1
