mux/mux2_4.v
module mux2_4(
  input [3:0] address_1,
  input [3:0] address_2,
  input select,
  output [3:0] address_out
  );

  assign address_out = select ? address_1 : address_2;

endmodule

mux/mux2_4_tb.v
`include "mux2_4.v"
module mux2_4_tb();
  reg clk = 0;

  reg [3:0] address_1 = 4'b0000;
  reg [3:0] address_2 = 4'b0000;
  reg select = 1'b0;
  wire [3:0] address_out = 4'bzzzz;

  initial begin
    clk = 1'b0;
    forever #2 clk = ~clk;
  end

  mux2_4 mx24(
    .address_1(address_1),
    .address_2(address_2),
    .select(select),
    .address_out(address_out)
    );

  initial begin
    $dumpfile("mux2_4_tb.vcd");
    $dumpvars(0, mux2_4_tb);

    for(integer i = 0; i < 12; i++) begin
      address_1++;
      address_2--;
      select++; #1;
      $display("address_out:%b address_1:%b address_2:%b select:%b", address_out, address_1, address_2, select); #20;
    end

    $display("Howdy");
    $finish;
  end
endmodule

mux/mux2_4_tb.vcd
$date
	Mon Mar 14 23:02:26 2022
$end
$version
	Icarus Verilog
$end
$timescale
	1s
$end
$scope module mux2_4_tb $end
$var wire 4 ! address_out [3:0] $end
$var reg 4 " address_1 [3:0] $end
$var reg 4 # address_2 [3:0] $end
$var reg 1 $ clk $end
$var reg 1 % select $end
$scope module mx24 $end
$var wire 4 & address_1 [3:0] $end
$var wire 4 ' address_2 [3:0] $end
$var wire 1 % select $end
$var wire 4 ( address_out [3:0] $end
$upscope $end
$scope begin $ivl_for_loop0 $end
$var integer 32 ) i [31:0] $end
$upscope $end
$upscope $end
$enddefinitions $end
#0
$dumpvars
b0 )
b1 (
b1111 '
b1 &
1%
0$
b1111 #
b1 "
b1 !
$end
#2
1$
#4
0$
#6
1$
#8
0$
#10
1$
#12
0$
#14
1$
#16
0$
#18
1$
#20
0$
#21
b1110 !
b1110 (
0%
b1110 #
b1110 '
b10 "
b10 &
b1 )
#22
1$
#24
0$
#26
1$
#28
0$
#30
1$
#32
0$
#34
1$
#36
0$
#38
1$
#40
0$
#42
b11 !
b11 (
1$
1%
b1101 #
b1101 '
b11 "
b11 &
b10 )
#44
0$
#46
1$
#48
0$
#50
1$
#52
0$
#54
1$
#56
0$
#58
1$
#60
0$
#62
1$
#63
b1100 !
b1100 (
0%
b1100 #
b1100 '
b100 "
b100 &
b11 )
#64
0$
#66
1$
#68
0$
#70
1$
#72
0$
#74
1$
#76
0$
#78
1$
#80
0$
#82
1$
#84
b101 !
b101 (
0$
1%
b1011 #
b1011 '
b101 "
b101 &
b100 )
#86
1$
#88
0$
#90
1$
#92
0$
#94
1$
#96
0$
#98
1$
#100
0$
#102
1$
#104
0$
#105
b1010 !
b1010 (
0%
b1010 #
b1010 '
b110 "
b110 &
b101 )
#106
1$
#108
0$
#110
1$
#112
0$
#114
1$
#116
0$
#118
1$
#120
0$
#122
1$
#124
0$
#126
b111 !
b111 (
1$
1%
b1001 #
b1001 '
b111 "
b111 &
b110 )
#128
0$
#130
1$
#132
0$
#134
1$
#136
0$
#138
1$
#140
0$
#142
1$
#144
0$
#146
1$
#147
b1000 !
b1000 (
0%
b1000 #
b1000 '
b1000 "
b1000 &
b111 )
#148
0$
#150
1$
#152
0$
#154
1$
#156
0$
#158
1$
#160
0$
#162
1$
#164
0$
#166
1$
#168
b1001 !
b1001 (
0$
1%
b111 #
b111 '
b1001 "
b1001 &
b1000 )
#170
1$
#172
0$
#174
1$
#176
0$
#178
1$
#180
0$
#182
1$
#184
0$
#186
1$
#188
0$
#189
b110 !
b110 (
0%
b110 #
b110 '
b1010 "
b1010 &
b1001 )
#190
1$
#192
0$
#194
1$
#196
0$
#198
1$
#200
0$
#202
1$
#204
0$
#206
1$
#208
0$
#210
b1011 !
b1011 (
1$
1%
b101 #
b101 '
b1011 "
b1011 &
b1010 )
#212
0$
#214
1$
#216
0$
#218
1$
#220
0$
#222
1$
#224
0$
#226
1$
#228
0$
#230
1$
#231
b100 !
b100 (
0%
b100 #
b100 '
b1100 "
b1100 &
b1011 )
#232
0$
#234
1$
#236
0$
#238
1$
#240
0$
#242
1$
#244
0$
#246
1$
#248
0$
#250
1$
#252
0$
b1100 )
