instruction_register/instruction_register.v
module instruction_register(
    input debug,
    input rst,
    input instr_load_in,
    input instr_send_in,
    input [7:0] bus_in,
    output [3:0] opcode,
    output [3:0] address_out
  );

  reg [3:0] high = 4'b0000;
  reg [3:0] low = 4'b0000;

  assign opcode = high;
  assign address_out = instr_send_in ? low : 4'bzzzz;

  always @(posedge rst) begin
    if(debug) $display("IR reset: %b", 8'b00000000);
    high <= 4'b0000;
    low <= 4'b0000;
  end

  always @(posedge instr_load_in or bus_in) begin
    if(debug) $display("IR loaded: %b %h", bus_in, opcode);
    high <= bus_in[7:4];
    low <= bus_in[3:0];
  end
endmodule

instruction_register/instruction_register_tb.v
`include "instruction_register.v"
module instruction_register_tb();
  reg clk;
  reg debug = 1;
  reg rst = 0;

  reg instr_load_in;
  reg instr_send_in;
  reg [7:0] bus_in;
  wire [3:0] opcode;
  wire [3:0] address_out;

  instruction_register ir(
      .debug(debug),
      .rst(rst),
      .instr_load_in(instr_load_in),
      .instr_send_in(instr_send_in),
      .bus_in(bus_in),
      .opcode(opcode),
      .address_out(address_out)
    );

    initial begin
      clk = 1'b0;
      forever #5 clk = ~clk;
    end

    initial begin
      rst = 1'b0;
      // bus_in = 8'b0;
    end

    initial begin
      $dumpfile("instruction_register_tb.vcd");
      $dumpvars(0, instruction_register_tb);

      for(integer i = 0; i < 12; i = i+1) begin
        bus_in = i * 10; #20;
        instr_load_in = i % 2 == 0;
        instr_send_in = !(i % 2 == 0);
        rst = (i % 6 == 0);
      end

      $display("Howdy");
      $finish;
    end

endmodule

instruction_register/instruction_register_tb.vcd
$date
	Sun Mar 13 22:17:25 2022
$end
$version
	Icarus Verilog
$end
$timescale
	1s
$end
$scope module instruction_register_tb $end
$var wire 4 ! opcode [3:0] $end
$var wire 4 " address_out [3:0] $end
$var reg 8 # bus_in [7:0] $end
$var reg 1 $ clk $end
$var reg 1 % debug $end
$var reg 1 & instr_load_in $end
$var reg 1 ' instr_send_in $end
$var reg 1 ( rst $end
$scope module ir $end
$var wire 8 ) bus_in [7:0] $end
$var wire 1 % debug $end
$var wire 1 & instr_load_in $end
$var wire 1 ' instr_send_in $end
$var wire 4 * opcode [3:0] $end
$var wire 1 ( rst $end
$var wire 4 + address_out [3:0] $end
$var reg 4 , high [3:0] $end
$var reg 4 - low [3:0] $end
$upscope $end
$scope begin $ivl_for_loop0 $end
$var integer 32 . i [31:0] $end
$upscope $end
$upscope $end
$enddefinitions $end
#0
$dumpvars
b0 .
b0 -
b0 ,
bx +
b0 *
b0 )
0(
x'
x&
1%
0$
b0 #
bx "
b0 !
$end
#5
1$
#10
0$
#15
1$
#20
b0 -
bz "
bz +
0$
b1010 #
b1010 )
b1 .
1(
0'
1&
#25
1$
#30
0$
#35
1$
#40
b100 -
b1 !
b1 *
b1 ,
b100 "
b100 +
0$
b10100 #
b10100 )
b10 .
0(
1'
0&
#45
1$
#50
0$
#55
1$
#60
b1110 -
bz "
bz +
0$
b11110 #
b11110 )
b11 .
0'
1&
#65
1$
#70
0$
#75
1$
#80
b1000 -
b10 !
b10 *
b10 ,
b1000 "
b1000 +
0$
b101000 #
b101000 )
b100 .
1'
0&
#85
1$
#90
0$
#95
1$
#100
b10 -
b11 !
b11 *
b11 ,
bz "
bz +
0$
b110010 #
b110010 )
b101 .
0'
1&
#105
1$
#110
0$
#115
1$
#120
b1100 -
b1100 "
b1100 +
0$
b111100 #
b111100 )
b110 .
1'
0&
#125
1$
#130
0$
#135
1$
#140
b0 -
b0 !
b0 *
b0 ,
bz "
bz +
0$
b1000110 #
b1000110 )
b111 .
1(
0'
1&
#145
1$
#150
0$
#155
1$
#160
b101 !
b101 *
b101 ,
b0 "
b0 +
0$
b1010000 #
b1010000 )
b1000 .
0(
1'
0&
#165
1$
#170
0$
#175
1$
#180
b1010 -
bz "
bz +
0$
b1011010 #
b1011010 )
b1001 .
0'
1&
#185
1$
#190
0$
#195
1$
#200
b100 -
b110 !
b110 *
b110 ,
b100 "
b100 +
0$
b1100100 #
b1100100 )
b1010 .
1'
0&
#205
1$
#210
0$
#215
1$
#220
b1110 -
bz "
bz +
0$
b1101110 #
b1101110 )
b1011 .
0'
1&
#225
1$
#230
0$
#235
1$
#240
b1110 "
b1110 +
0$
b1100 .
1'
0&
