alu/alu.v
module alu(
  input [7:0] a, b,
  input sub, debug, sum_wr,
  output carry_flg, zero_flg,
  output [7:0] bus
  );

  reg [8:0] sum = 9'b000000000;
  reg carry_flg_ = 1'b0;
  reg zero_flg_ = 1'b0;

  assign carry_flg = carry_flg_;
  assign zero_flg = zero_flg_;
  assign bus = sum_wr ? sum : 8'bzzzzzzzz;

  always @(posedge sum_wr) begin
    sum = sub ? a + ~b + 1'b1 : a + b;
    carry_flg_ = sum[8];
    zero_flg_ = sum == 9'b000000000;
    if (debug) $display("%d %s %d = %d CARRY: %b ZERO: %b", a, sub ? "-" : "+", b, sum, carry_flg, zero_flg);
  end
endmodule

alu/alu_tb.v
`timescale 1 ns/10 ps
`include "alu.v"
module alu_tb();
  reg clk = 0;
  reg [7:0] a, b;
  wire [1:0] flags;
  reg sub = 0, sum_wr;
  wire [7:0] bus;
  reg debug = 1;

  alu alu_(
    .a(a),
    .b(b),
    .sub(sub),
    .sum_wr(sum_wr),
    .carry_flg(carry_flg),
    .zero_flg(zero_flg),
    .bus(bus),
    .debug(debug)
    );

  initial begin
    clk = 1'b0;
    forever #2 clk = ~clk;
  end

  initial begin
    $dumpfile("alu_tb.vcd");
    $dumpvars(0, alu_tb);

    for(integer i = 0; i < 12; i++) begin
      sum_wr = 1;
      b = 8'b00000000 + i;
      a = 8'b11111100 + i; #20;
      sum_wr = 0;
    end

    for(integer i = 0; i < 12; i++) begin
      sub = 1;
      sum_wr = 1;
      a = 8'b00001000;
      b = i; #20;
      sum_wr = 0;
    end

    $display("Howdy");
    $finish;
  end
endmodule

alu/alu_tb.vcd
$date
	Wed Mar 16 23:44:01 2022
$end
$version
	Icarus Verilog
$end
$timescale
	10ps
$end
$scope module alu_tb $end
$var wire 1 ! zero_flg $end
$var wire 1 " carry_flg $end
$var wire 8 # bus [7:0] $end
$var reg 8 $ a [7:0] $end
$var reg 8 % b [7:0] $end
$var reg 1 & clk $end
$var reg 1 ' debug $end
$var reg 1 ( sub $end
$var reg 1 ) sum_wr $end
$scope module alu_ $end
$var wire 8 * a [7:0] $end
$var wire 8 + b [7:0] $end
$var wire 1 " carry_flg $end
$var wire 1 ' debug $end
$var wire 1 ( sub $end
$var wire 1 ) sum_wr $end
$var wire 1 ! zero_flg $end
$var wire 8 , bus [7:0] $end
$var reg 1 - carry_flg_ $end
$var reg 9 . sum [8:0] $end
$var reg 1 / zero_flg_ $end
$upscope $end
$scope begin $ivl_for_loop0 $end
$var integer 32 0 i [31:0] $end
$upscope $end
$scope begin $ivl_for_loop1 $end
$var integer 32 1 i [31:0] $end
$upscope $end
$upscope $end
$enddefinitions $end
#0
$dumpvars
bx 1
b0 0
0/
b11111100 .
0-
b11111100 ,
b0 +
b11111100 *
1)
0(
1'
0&
b0 %
b11111100 $
b11111100 #
0"
0!
$end
#200
1&
#400
0&
#600
1&
#800
0&
#1000
1&
#1200
0&
#1400
1&
#1600
0&
#1800
1&
#2000
b11111110 #
b11111110 ,
b11111110 .
0&
b11111101 $
b11111101 *
b1 %
b1 +
b1 0
1)
#2200
1&
#2400
0&
#2600
1&
#2800
0&
#3000
1&
#3200
0&
#3400
1&
#3600
0&
#3800
1&
#4000
b0 #
b0 ,
1"
1-
b100000000 .
0&
b11111110 $
b11111110 *
b10 %
b10 +
b10 0
1)
#4200
1&
#4400
0&
#4600
1&
#4800
0&
#5000
1&
#5200
0&
#5400
1&
#5600
0&
#5800
1&
#6000
b10 #
b10 ,
b100000010 .
0&
b11111111 $
b11111111 *
b11 %
b11 +
b11 0
1)
#6200
1&
#6400
0&
#6600
1&
#6800
0&
#7000
1&
#7200
0&
#7400
1&
#7600
0&
#7800
1&
#8000
b100 #
b100 ,
0"
0-
b100 .
0&
b0 $
b0 *
b100 %
b100 +
b100 0
1)
#8200
1&
#8400
0&
#8600
1&
#8800
0&
#9000
1&
#9200
0&
#9400
1&
#9600
0&
#9800
1&
#10000
b110 #
b110 ,
b110 .
0&
b1 $
b1 *
b101 %
b101 +
b101 0
1)
#10200
1&
#10400
0&
#10600
1&
#10800
0&
#11000
1&
#11200
0&
#11400
1&
#11600
0&
#11800
1&
#12000
b1000 #
b1000 ,
b1000 .
0&
b10 $
b10 *
b110 %
b110 +
b110 0
1)
#12200
1&
#12400
0&
#12600
1&
#12800
0&
#13000
1&
#13200
0&
#13400
1&
#13600
0&
#13800
1&
#14000
b1010 #
b1010 ,
b1010 .
0&
b11 $
b11 *
b111 %
b111 +
b111 0
1)
#14200
1&
#14400
0&
#14600
1&
#14800
0&
#15000
1&
#15200
0&
#15400
1&
#15600
0&
#15800
1&
#16000
b1100 #
b1100 ,
b1100 .
0&
b100 $
b100 *
b1000 %
b1000 +
b1000 0
1)
#16200
1&
#16400
0&
#16600
1&
#16800
0&
#17000
1&
#17200
0&
#17400
1&
#17600
0&
#17800
1&
#18000
b1110 #
b1110 ,
b1110 .
0&
b101 $
b101 *
b1001 %
b1001 +
b1001 0
1)
#18200
1&
#18400
0&
#18600
1&
#18800
0&
#19000
1&
#19200
0&
#19400
1&
#19600
0&
#19800
1&
#20000
b10000 #
b10000 ,
b10000 .
0&
b110 $
b110 *
b1010 %
b1010 +
b1010 0
1)
#20200
1&
#20400
0&
#20600
1&
#20800
0&
#21000
1&
#21200
0&
#21400
1&
#21600
0&
#21800
1&
#22000
b10010 #
b10010 ,
b10010 .
0&
b111 $
b111 *
b1011 %
b1011 +
b1011 0
1)
#22200
1&
#22400
0&
#22600
1&
#22800
0&
#23000
1&
#23200
0&
#23400
1&
#23600
0&
#23800
1&
#24000
b1000 #
b1000 ,
b1000 .
0&
b0 %
b0 +
b1000 $
b1000 *
1(
b0 1
b1100 0
1)
#24200
1&
#24400
0&
#24600
1&
#24800
0&
#25000
1&
#25200
0&
#25400
1&
#25600
0&
#25800
1&
#26000
b111 #
b111 ,
b111 .
0&
b1 %
b1 +
b1 1
1)
#26200
1&
#26400
0&
#26600
1&
#26800
0&
#27000
1&
#27200
0&
#27400
1&
#27600
0&
#27800
1&
#28000
b110 #
b110 ,
b110 .
0&
b10 %
b10 +
b10 1
1)
#28200
1&
#28400
0&
#28600
1&
#28800
0&
#29000
1&
#29200
0&
#29400
1&
#29600
0&
#29800
1&
#30000
b101 #
b101 ,
b101 .
0&
b11 %
b11 +
b11 1
1)
#30200
1&
#30400
0&
#30600
1&
#30800
0&
#31000
1&
#31200
0&
#31400
1&
#31600
0&
#31800
1&
#32000
b100 #
b100 ,
b100 .
0&
b100 %
b100 +
b100 1
1)
#32200
1&
#32400
0&
#32600
1&
#32800
0&
#33000
1&
#33200
0&
#33400
1&
#33600
0&
#33800
1&
#34000
b11 #
b11 ,
b11 .
0&
b101 %
b101 +
b101 1
1)
#34200
1&
#34400
0&
#34600
1&
#34800
0&
#35000
1&
#35200
0&
#35400
1&
#35600
0&
#35800
1&
#36000
b10 #
b10 ,
b10 .
0&
b110 %
b110 +
b110 1
1)
#36200
1&
#36400
0&
#36600
1&
#36800
0&
#37000
1&
#37200
0&
#37400
1&
#37600
0&
#37800
1&
#38000
b1 #
b1 ,
b1 .
0&
b111 %
b111 +
b111 1
1)
#38200
1&
#38400
0&
#38600
1&
#38800
0&
#39000
1&
#39200
0&
#39400
1&
#39600
0&
#39800
1&
#40000
b0 #
b0 ,
1!
1/
b0 .
0&
b1000 %
b1000 +
b1000 1
1)
#40200
1&
#40400
0&
#40600
1&
#40800
0&
#41000
1&
#41200
0&
#41400
1&
#41600
0&
#41800
1&
#42000
b11111111 #
b11111111 ,
0!
0/
1"
1-
b111111111 .
0&
b1001 %
b1001 +
b1001 1
1)
#42200
1&
#42400
0&
#42600
1&
#42800
0&
#43000
1&
#43200
0&
#43400
1&
#43600
0&
#43800
1&
#44000
b11111110 #
b11111110 ,
b111111110 .
0&
b1010 %
b1010 +
b1010 1
1)
#44200
1&
#44400
0&
#44600
1&
#44800
0&
#45000
1&
#45200
0&
#45400
1&
#45600
0&
#45800
1&
#46000
b11111101 #
b11111101 ,
b111111101 .
0&
b1011 %
b1011 +
b1011 1
1)
#46200
1&
#46400
0&
#46600
1&
#46800
0&
#47000
1&
#47200
0&
#47400
1&
#47600
0&
#47800
1&
#48000
bz #
bz ,
0&
b1100 1
0)
